django_universal_paginator/__init__.py
django_universal_paginator/constants.py
django_universal_paginator/converter.py
django_universal_paginator/cursor.py
django_universal_paginator/settings.py
django_universal_paginator/utils.py
django_universal_paginator/templates/paginator/paginator.html
django_universal_paginator/templatetags/__init__.py
django_universal_paginator/templatetags/paginator_tags.py
django_universal_paginator-1.4.0.dist-info/AUTHORS
django_universal_paginator-1.4.0.dist-info/LICENSE
django_universal_paginator-1.4.0.dist-info/METADATA
django_universal_paginator-1.4.0.dist-info/WHEEL
django_universal_paginator-1.4.0.dist-info/top_level.txt
django_universal_paginator-1.4.0.dist-info/RECORD
