Metadata-Version: 2.1
Name: django-universal-paginator
Version: 1.4.0
Summary: Simple pagination for django
Author-email: Miroslav Bendík <miroslav.bendik@gmail.com>
License: MIT
Project-URL: homepage, https://github.com/mireq/django-universal-paginator
Project-URL: documentation, https://github.com/mireq/django-universal-paginator
Project-URL: repository, https://github.com/mireq/django-universal-paginator
Project-URL: changelog, https://github.com/mireq/django-universal-paginator/blob/master/CHANGELOG.md
Keywords: pagination,cursor,simple,cursor pagination,simple pagination
Classifier: Programming Language :: Python :: 3
Requires-Python: >=3.7
License-File: LICENSE
License-File: AUTHORS
Requires-Dist: django
Provides-Extra: dev
Requires-Dist: tox ; extra == 'dev'
Requires-Dist: pylint ; extra == 'dev'
Requires-Dist: pre-commit ; extra == 'dev'
Requires-Dist: bump2version ; extra == 'dev'
Requires-Dist: commitizen ; extra == 'dev'
Requires-Dist: django-jinja ; extra == 'dev'
